{"Date":"2022/3/2","ALL":"72591","Hokkaido":"2232","Aomori":"486","Iwate":"319","Miyagi":"783","Akita":"237","Yamagata":"212","Fukushima":"398","Ibaraki":"1334","Tochigi":"757","Gunma":"789","Saitama":"4617","Chiba":"3824","Tokyo":"12693","Kanagawa":"6205","Niigata":"431","Toyama":"628","Ishikawa":"518","Fukui":"347","Yamanashi":"279","Nagano":"445","Gifu":"644","Shizuoka":"1404","Aichi":"5225","Mie":"665","Shiga":"881","Kyoto":"1969","Osaka":"9219","Hyogo":"3788","Nara":"1087","Wakayama":"273","Tottori":"106","Shimane":"97","Okayama":"824","Hiroshima":"736","Yamaguchi":"305","Tokushima":"280","Kagawa":"436","Ehime":"302","Kochi":"205","Fukuoka":"3073","Saga":"373","Nagasaki":"417","Kumamoto":"701","Oita":"392","Miyazaki":"220","Kagoshima":"469","Okinawa":"966"}