{"Date":"2022/4/12","ALL":"49694","Hokkaido":"1905","Aomori":"494","Iwate":"293","Miyagi":"609","Akita":"445","Yamagata":"235","Fukushima":"539","Ibaraki":"949","Tochigi":"664","Gunma":"593","Saitama":"2541","Chiba":"2279","Tokyo":"6922","Kanagawa":"4117","Niigata":"517","Toyama":"129","Ishikawa":"175","Fukui":"217","Yamanashi":"286","Nagano":"697","Gifu":"842","Shizuoka":"846","Aichi":"3401","Mie":"506","Shiga":"375","Kyoto":"732","Osaka":"5051","Hyogo":"1826","Nara":"346","Wakayama":"384","Tottori":"98","Shimane":"150","Okayama":"566","Hiroshima":"908","Yamaguchi":"322","Tokushima":"117","Kagawa":"402","Ehime":"449","Kochi":"184","Fukuoka":"2321","Saga":"612","Nagasaki":"490","Kumamoto":"855","Oita":"496","Miyazaki":"571","Kagoshima":"729","Okinawa":"1509"}