{"Date":"2022/9/13","ALL":"87548","Hokkaido":"2367","Aomori":"470","Iwate":"446","Miyagi":"1729","Akita":"915","Yamagata":"862","Fukushima":"1197","Ibaraki":"589","Tochigi":"1468","Gunma":"1613","Saitama":"2982","Chiba":"3131","Tokyo":"8855","Kanagawa":"4279","Niigata":"687","Toyama":"889","Ishikawa":"385","Fukui":"357","Yamanashi":"615","Nagano":"1492","Gifu":"2344","Shizuoka":"3181","Aichi":"8757","Mie":"542","Shiga":"1419","Kyoto":"1359","Osaka":"9617","Hyogo":"3859","Nara":"520","Wakayama":"660","Tottori":"380","Shimane":"681","Okayama":"1300","Hiroshima":"1599","Yamaguchi":"1019","Tokushima":"474","Kagawa":"1049","Ehime":"1184","Kochi":"817","Fukuoka":"3179","Saga":"874","Nagasaki":"1121","Kumamoto":"1530","Oita":"939","Miyazaki":"1053","Kagoshima":"1932","Okinawa":"831"}