{"Date":"2022/9/14","ALL":"100249","Hokkaido":"3721","Aomori":"837","Iwate":"794","Miyagi":"1295","Akita":"750","Yamagata":"1198","Fukushima":"1471","Ibaraki":"2070","Tochigi":"1339","Gunma":"1440","Saitama":"6039","Chiba":"4416","Tokyo":"10593","Kanagawa":"5139","Niigata":"1632","Toyama":"1053","Ishikawa":"1034","Fukui":"930","Yamanashi":"468","Nagano":"1479","Gifu":"1519","Shizuoka":"3507","Aichi":"7155","Mie":"2291","Shiga":"1209","Kyoto":"2575","Osaka":"7719","Hyogo":"4572","Nara":"1414","Wakayama":"661","Tottori":"273","Shimane":"402","Okayama":"1812","Hiroshima":"3095","Yamaguchi":"936","Tokushima":"648","Kagawa":"1000","Ehime":"908","Kochi":"759","Fukuoka":"2688","Saga":"586","Nagasaki":"760","Kumamoto":"1466","Oita":"771","Miyazaki":"1148","Kagoshima":"1853","Okinawa":"824"}