{"Date":"2022/3/24","ALL":"49821","Hokkaido":"2048","Aomori":"574","Iwate":"242","Miyagi":"699","Akita":"238","Yamagata":"170","Fukushima":"444","Ibaraki":"933","Tochigi":"681","Gunma":"605","Saitama":"3573","Chiba":"2340","Tokyo":"8875","Kanagawa":"3742","Niigata":"537","Toyama":"325","Ishikawa":"297","Fukui":"161","Yamanashi":"203","Nagano":"478","Gifu":"516","Shizuoka":"1012","Aichi":"3224","Mie":"557","Shiga":"685","Kyoto":"963","Osaka":"4490","Hyogo":"2325","Nara":"495","Wakayama":"198","Tottori":"138","Shimane":"77","Okayama":"517","Hiroshima":"920","Yamaguchi":"267","Tokushima":"124","Kagawa":"420","Ehime":"265","Kochi":"165","Fukuoka":"2321","Saga":"244","Nagasaki":"294","Kumamoto":"434","Oita":"292","Miyazaki":"193","Kagoshima":"539","Okinawa":"981"}