{"Date":"2022/12/15","ALL":"168491","Hokkaido":"6371","Aomori":"1813","Iwate":"1816","Miyagi":"4016","Akita":"1214","Yamagata":"1429","Fukushima":"2959","Ibaraki":"4531","Tochigi":"2973","Gunma":"2956","Saitama":"9142","Chiba":"7751","Tokyo":"17687","Kanagawa":"11040","Niigata":"3251","Toyama":"1329","Ishikawa":"1460","Fukui":"1164","Yamanashi":"1100","Nagano":"2941","Gifu":"3227","Shizuoka":"4646","Aichi":"9810","Mie":"2895","Shiga":"1788","Kyoto":"2999","Osaka":"9586","Hyogo":"6742","Nara":"1603","Wakayama":"1291","Tottori":"1149","Shimane":"1084","Okayama":"3087","Hiroshima":"5173","Yamaguchi":"1707","Tokushima":"918","Kagawa":"1192","Ehime":"2044","Kochi":"876","Fukuoka":"7809","Saga":"1636","Nagasaki":"1542","Kumamoto":"3152","Oita":"1887","Miyazaki":"1472","Kagoshima":"1444","Okinawa":"789"}