{"Date":"2023/2/13","ALL":"9423","Hokkaido":"324","Aomori":"50","Iwate":"88","Miyagi":"187","Akita":"46","Yamagata":"77","Fukushima":"165","Ibaraki":"170","Tochigi":"208","Gunma":"181","Saitama":"463","Chiba":"341","Tokyo":"810","Kanagawa":"600","Niigata":"100","Toyama":"99","Ishikawa":"83","Fukui":"53","Yamanashi":"64","Nagano":"198","Gifu":"296","Shizuoka":"418","Aichi":"445","Mie":"189","Shiga":"85","Kyoto":"135","Osaka":"624","Hyogo":"302","Nara":"104","Wakayama":"133","Tottori":"108","Shimane":"84","Okayama":"191","Hiroshima":"332","Yamaguchi":"229","Tokushima":"87","Kagawa":"95","Ehime":"160","Kochi":"73","Fukuoka":"289","Saga":"72","Nagasaki":"116","Kumamoto":"154","Oita":"116","Miyazaki":"78","Kagoshima":"150","Okinawa":"51"}