{"Date":"2022/4/30","ALL":"25107","Hokkaido":"2502","Aomori":"268","Iwate":"195","Miyagi":"277","Akita":"179","Yamagata":"102","Fukushima":"325","Ibaraki":"614","Tochigi":"236","Gunma":"196","Saitama":"1339","Chiba":"1075","Tokyo":"2979","Kanagawa":"2575","Niigata":"322","Toyama":"68","Ishikawa":"328","Fukui":"194","Yamanashi":"59","Nagano":"248","Gifu":"313","Shizuoka":"430","Aichi":"951","Mie":"252","Shiga":"236","Kyoto":"426","Osaka":"1114","Hyogo":"809","Nara":"221","Wakayama":"164","Tottori":"51","Shimane":"75","Okayama":"324","Hiroshima":"743","Yamaguchi":"113","Tokushima":"37","Kagawa":"131","Ehime":"117","Kochi":"96","Fukuoka":"1623","Saga":"290","Nagasaki":"301","Kumamoto":"390","Oita":"230","Miyazaki":"261","Kagoshima":"461","Okinawa":"867"}