{"Date":"2022/11/24","ALL":"60108","Hokkaido":"4895","Aomori":"673","Iwate":"680","Miyagi":"2726","Akita":"299","Yamagata":"661","Fukushima":"1355","Ibaraki":"1194","Tochigi":"856","Gunma":"1035","Saitama":"2345","Chiba":"2239","Tokyo":"5639","Kanagawa":"4708","Niigata":"1563","Toyama":"526","Ishikawa":"558","Fukui":"510","Yamanashi":"575","Nagano":"2555","Gifu":"759","Shizuoka":"2050","Aichi":"2592","Mie":"1745","Shiga":"597","Kyoto":"786","Osaka":"2644","Hyogo":"2206","Nara":"550","Wakayama":"358","Tottori":"351","Shimane":"300","Okayama":"1100","Hiroshima":"3664","Yamaguchi":"341","Tokushima":"115","Kagawa":"201","Ehime":"316","Kochi":"174","Fukuoka":"1339","Saga":"211","Nagasaki":"343","Kumamoto":"418","Oita":"543","Miyazaki":"279","Kagoshima":"284","Okinawa":"250"}