{"Date":"2022/4/8","ALL":"51867","Hokkaido":"2216","Aomori":"512","Iwate":"343","Miyagi":"605","Akita":"365","Yamagata":"158","Fukushima":"642","Ibaraki":"1305","Tochigi":"614","Gunma":"594","Saitama":"3580","Chiba":"2627","Tokyo":"8112","Kanagawa":"3717","Niigata":"860","Toyama":"190","Ishikawa":"325","Fukui":"225","Yamanashi":"223","Nagano":"675","Gifu":"631","Shizuoka":"1024","Aichi":"2853","Mie":"736","Shiga":"354","Kyoto":"962","Osaka":"3908","Hyogo":"2018","Nara":"527","Wakayama":"272","Tottori":"75","Shimane":"113","Okayama":"602","Hiroshima":"1199","Yamaguchi":"366","Tokushima":"108","Kagawa":"288","Ehime":"340","Kochi":"167","Fukuoka":"2876","Saga":"429","Nagasaki":"392","Kumamoto":"680","Oita":"442","Miyazaki":"612","Kagoshima":"677","Okinawa":"1328"}