{"Date":"2022/12/14","ALL":"190607","Hokkaido":"7214","Aomori":"2034","Iwate":"1907","Miyagi":"4704","Akita":"1531","Yamagata":"1712","Fukushima":"3472","Ibaraki":"4700","Tochigi":"3279","Gunma":"3322","Saitama":"10684","Chiba":"8669","Tokyo":"18812","Kanagawa":"11320","Niigata":"3991","Toyama":"1739","Ishikawa":"1758","Fukui":"1596","Yamanashi":"1331","Nagano":"3595","Gifu":"3492","Shizuoka":"5837","Aichi":"11904","Mie":"3364","Shiga":"2270","Kyoto":"3334","Osaka":"10335","Hyogo":"7656","Nara":"1892","Wakayama":"1546","Tottori":"1365","Shimane":"1331","Okayama":"3101","Hiroshima":"5519","Yamaguchi":"1867","Tokushima":"1020","Kagawa":"1496","Ehime":"2318","Kochi":"1090","Fukuoka":"9084","Saga":"1842","Nagasaki":"1771","Kumamoto":"3538","Oita":"2099","Miyazaki":"1754","Kagoshima":"1578","Okinawa":"834"}